garf/executors/__init__.py
garf/executors/api_executor.py
garf/executors/bq_executor.py
garf/executors/config.py
garf/executors/exceptions.py
garf/executors/execution_context.py
garf/executors/executor.py
garf/executors/fetchers.py
garf/executors/garf_pb2.py
garf/executors/garf_pb2_grpc.py
garf/executors/query_processor.py
garf/executors/sql_executor.py
garf/executors/telemetry.py
garf/executors/workflow.py
garf/executors/entrypoints/__init__.py
garf/executors/entrypoints/cli.py
garf/executors/entrypoints/grpc_server.py
garf/executors/entrypoints/server.py
garf/executors/entrypoints/tracer.py
garf/executors/entrypoints/utils.py
garf_executors/__init__.py
garf_executors/api_executor.py
garf_executors/bq_executor.py
garf_executors/config.py
garf_executors/exceptions.py
garf_executors/execution_context.py
garf_executors/executor.py
garf_executors/fetchers.py
garf_executors/sql_executor.py
garf_executors/telemetry.py
garf_executors/workflow.py
garf_executors/entrypoints/__init__.py
garf_executors/entrypoints/cli.py
garf_executors/entrypoints/grcp_server.py
garf_executors/entrypoints/server.py
garf_executors/entrypoints/tracer.py
garf_executors/entrypoints/utils.py
garf_executors-1.0.2.dist-info/METADATA
garf_executors-1.0.2.dist-info/WHEEL
garf_executors-1.0.2.dist-info/entry_points.txt
garf_executors-1.0.2.dist-info/top_level.txt
garf_executors-1.0.2.dist-info/RECORD
