Metadata-Version: 2.4
Name: garf-executors
Version: 1.0.2
Summary: Executes queries against API and writes data to local/remote storage.
Author-email: "Google Inc. (gTech gPS CSE team)" <no-reply@google.com>, Andrei Markin <andrey.markin.ppc@gmail.com>
License: Apache 2.0
Classifier: Programming Language :: Python :: 3 :: Only
Classifier: Programming Language :: Python :: 3.9
Classifier: Programming Language :: Python :: 3.10
Classifier: Programming Language :: Python :: 3.11
Classifier: Programming Language :: Python :: 3.12
Classifier: Programming Language :: Python :: 3.13
Classifier: Programming Language :: Python :: 3.14
Classifier: Intended Audience :: Developers
Classifier: Topic :: Software Development :: Libraries :: Python Modules
Classifier: Operating System :: OS Independent
Classifier: License :: OSI Approved :: Apache Software License
Requires-Python: >=3.9
Requires-Dist: garf-core>=1.0.0
Requires-Dist: garf-io>=1.0.0
Requires-Dist: pyyaml
Requires-Dist: pydantic
Requires-Dist: opentelemetry-api
Requires-Dist: opentelemetry-sdk
Requires-Dist: opentelemetry-exporter-otlp
Provides-Extra: bq
Requires-Dist: garf-io[bq]; extra == "bq"
Requires-Dist: pandas; extra == "bq"
Requires-Dist: google-cloud-logging; extra == "bq"
Requires-Dist: smart_open[gcs]; extra == "bq"
Provides-Extra: sql
Requires-Dist: garf-io[sqlalchemy]; extra == "sql"
Requires-Dist: pandas; extra == "sql"
Provides-Extra: gcp
Requires-Dist: opentelemetry-exporter-gcp-trace; extra == "gcp"
Provides-Extra: server
Requires-Dist: fastapi[standard]; extra == "server"
Requires-Dist: opentelemetry-instrumentation-fastapi; extra == "server"
Requires-Dist: typer; extra == "server"
Provides-Extra: all
Requires-Dist: garf-executors[bq,gcp,server,sql]; extra == "all"
